pakakit/__init__.py
pakakit/paka.py
pakakit-0.0.1.dist-info/LICENSE
pakakit-0.0.1.dist-info/METADATA
pakakit-0.0.1.dist-info/WHEEL
pakakit-0.0.1.dist-info/top_level.txt
pakakit-0.0.1.dist-info/RECORD
