Metadata-Version: 2.1
Name: pakakit
Version: 0.0.1
Summary: This program  determines matching positions of patterns in a sequence
Author-email: Clabe Wekesa <simiyu86wekesa@gmail.com>
Project-URL: Homepage, https://github.com/Clabe1986/pakakit
Project-URL: Bug Tracker, https://github.com/Clabe1986/pakakit/issues
Classifier: Programming Language :: Python :: 3
Classifier: License :: OSI Approved :: MIT License
Classifier: Operating System :: OS Independent
Requires-Python: >=3.7
License-File: LICENSE
